Ifte_Stuff/mips_cpu_pc.v
module mips_cpu_pc(
    input logic clk,
    input logic reset,
    input logic[5:0] opcode,
    input logic[5:0] funct,
    input logic[4:0] rt,
    input logic[4:0] sa,
    input logic[4:0] rd,
    input logic[31:0] rs_data, // received from register
    input logic[15:0] offset,
    input logic[25:0] target,
    input logic[3:0] control, // rs==rt | rs > 0 | rs == 0 | rs < 0
    output logic[31:0] pc = 32'hBFC00000,
    output logic[31:0] regstore
);

    logic[31:0] dest; // stores address after delay slot
    logic delayflag = 0;
    logic[31:0] pc_inc;

    assign pc_inc = pc + 4;

    always_ff @(posedge clk) begin
        if (reset == 1) begin
            pc <= 32'hBFC00000;
            dest <= 0;
            delayflag <= 0;
            regstore <= 0;
        end else begin
            if (opcode == 000010) begin                                                     //j
                dest <= { 4'b0000, target, 2'b00 } + { pc_inc[31:28], 28'b0000000000000000000000000000 };
                pc <= pc + 4;
                delayflag <= 1;
            end else if (opcode == 000011) begin                                            //jal
                regstore <= pc + 8; //goes to r31
                dest <= { 4'b0000, target, 2'b00 } + { pc_inc[31:28], 28'b0000000000000000000000000000 };
                pc <= pc + 4;
                delayflag <= 1;
            end else if (opcode == 0 && funct == 6'b001001 && rt == 0 && sa == 0) begin     //jalr
                regstore <= pc + 8; //goes to rd
                dest <= rs_data;
                pc <= pc + 4;
                delayflag <= 1;
            end else if (
            opcode == 0 && funct == 6'b001000 && rt == 0 && rd == 0 && sa == 0              //jr
            ) begin
                dest <= rs_data;
                pc <= pc + 4;
                delayflag <= 1;
            end else if (
            opcode == 6'b000100 && control[3] == 1 ||                                       //beq
            opcode == 6'b000101 && control[3] != 1 ||                                       //bne
            opcode == 6'b000111 && rt == 5'b00000 && control[2] == 1 ||                     //bgtz
            opcode == 6'b000001 && rt == 5'b00000 && control[0] == 1 ||                     //bltz
            opcode == 6'b000000 && rt == 5'b00001 && (control[1] == 1 || control[2] == 1) ||//bgez
            opcode == 6'b000000 && rt == 5'b00000 && (control[1] == 1 || control[0] == 1)   //blez
            ) begin
                dest <= pc + 4 + { {14{ offset[15] }}, offset, 2'b00 };
                pc <= pc + 4;
                delayflag <= 1;
            end else if (
            opcode == 6'b000001 && rt == 5'b10001 && (control[1] == 1 || control[2] == 1) ||//bgezal
            opcode == 6'b000000 && rt == 5'b00001 && control[0] == 1                        //bltzal
            ) begin
                regstore <= pc + 8; //goes to r31
                dest <= pc + 4 + { {14{ offset[15] }}, offset, 2'b00 };
                pc <= pc + 4;
                delayflag <= 1;
            end else if (delayflag == 1) begin
                pc <= dest;
                delayflag <= 0;
            end else begin
                pc <= pc + 4;
            end
        end
    end

endmodule

Ifte_Stuff/pc_tb.v
module pc_tb();

    logic clk;
    logic reset;
    logic[5:0] opcode;
    logic[5:0] funct;
    logic[4:0] rt;
    logic[4:0] sa;
    logic[4:0] rd;
    logic[31:0] rs_data; //received from register
    logic[15:0] offset;
    logic[25:0] target;
    logic[3:0] control; // rs==rt | rs > 0 | rs == 0 | rs < 0
    logic[31:0] pc; //10111111110000000000000000000000
    logic[31:0] regstore;

    initial begin
        $dumpfile("pc_tb.vcd");
        $dumpvars(0, pc_tb);

        clk = 0;
        repeat(1000) begin
            #10;
            clk = !clk;
            #10;
            clk = !clk;
        end
    end

    initial begin
        #5;
        $display("Initial PC value: %b", pc);
        opcode = 6'b000010;
        target = 26'b01010101010111111111010101;
        reset = 0;

        #10;
        $display("PC value: %b", pc);
        opcode = 0;
        sa = 0;
        funct = 6'b100000;

        #10;
        #10;
        $display("PC value: %b", pc);

        #10;
        #10;
        $display("PC value: %b", pc);

        #10;
        #10;
        $display("PC value: %b", pc);

        #10;
        #10;
        $display("PC value: %b", pc);

        #10;
        #10;
        $display("PC value: %b", pc);

        #10;
        #10;
        $display("PC value: %b", pc);
    end

    mips_cpu_pc dut(
        .clk(clk),
        .reset(reset),
        .opcode(opcode),
        .funct(funct),
        .rt(rt),
        .sa(sa),
        .rd(rd),
        .rs_data(rs_data),
        .offset(offset),
        .target(target),
        .control(control),
        .pc(pc),
        .regstore(regstore)
    );

endmodule

Ifte_Stuff/pc_tb.vcd
$date
	Mon Dec  6 16:09:22 2021
$end
$version
	Icarus Verilog
$end
$timescale
	1s
$end
$scope module pc_tb $end
$var wire 32 ! regstore [31:0] $end
$var wire 32 " pc [31:0] $end
$var reg 1 # clk $end
$var reg 4 $ control [3:0] $end
$var reg 6 % funct [5:0] $end
$var reg 16 & offset [15:0] $end
$var reg 6 ' opcode [5:0] $end
$var reg 5 ( rd [4:0] $end
$var reg 1 ) reset $end
$var reg 32 * rs_data [31:0] $end
$var reg 5 + rt [4:0] $end
$var reg 5 , sa [4:0] $end
$var reg 26 - target [25:0] $end
$scope module dut $end
$var wire 1 # clk $end
$var wire 4 . control [3:0] $end
$var wire 6 / funct [5:0] $end
$var wire 16 0 offset [15:0] $end
$var wire 6 1 opcode [5:0] $end
$var wire 5 2 rd [4:0] $end
$var wire 1 ) reset $end
$var wire 32 3 rs_data [31:0] $end
$var wire 5 4 rt [4:0] $end
$var wire 5 5 sa [4:0] $end
$var wire 26 6 target [25:0] $end
$var wire 32 7 pc_inc [31:0] $end
$var reg 1 8 delayflag $end
$var reg 32 9 dest [31:0] $end
$var reg 32 : pc [31:0] $end
$var reg 32 ; regstore [31:0] $end
$upscope $end
$upscope $end
$enddefinitions $end
#0
$dumpvars
bx ;
b10111111110000000000000000000000 :
bx 9
08
b10111111110000000000000000000100 7
bx 6
bx 5
bx 4
bx 3
bx 2
bx 1
bx 0
bx /
bx .
bx -
bx ,
bx +
bx *
x)
bx (
bx '
bx &
bx %
bx $
0#
b10111111110000000000000000000000 "
bx !
$end
#5
0)
b1010101010111111111010101 -
b1010101010111111111010101 6
b10 '
b10 1
#10
b10111111110000000000000000001000 7
b10111111110000000000000000000100 "
b10111111110000000000000000000100 :
1#
#15
b100000 %
b100000 /
b0 ,
b0 5
b0 '
b0 1
#20
0#
#30
b10111111110000000000000000001100 7
b10111111110000000000000000001000 "
b10111111110000000000000000001000 :
1#
#40
0#
#50
b10111111110000000000000000010000 7
b10111111110000000000000000001100 "
b10111111110000000000000000001100 :
1#
#60
0#
#70
b10111111110000000000000000010100 7
b10111111110000000000000000010000 "
b10111111110000000000000000010000 :
1#
#80
0#
#90
b10111111110000000000000000011000 7
b10111111110000000000000000010100 "
b10111111110000000000000000010100 :
1#
#100
0#
#110
b10111111110000000000000000011100 7
b10111111110000000000000000011000 "
b10111111110000000000000000011000 :
1#
#120
0#
#130
b10111111110000000000000000100000 7
b10111111110000000000000000011100 "
b10111111110000000000000000011100 :
1#
#140
0#
#150
b10111111110000000000000000100100 7
b10111111110000000000000000100000 "
b10111111110000000000000000100000 :
1#
#160
0#
#170
b10111111110000000000000000101000 7
b10111111110000000000000000100100 "
b10111111110000000000000000100100 :
1#
#180
0#
#190
b10111111110000000000000000101100 7
b10111111110000000000000000101000 "
b10111111110000000000000000101000 :
1#
#200
0#
#210
b10111111110000000000000000110000 7
b10111111110000000000000000101100 "
b10111111110000000000000000101100 :
1#
#220
0#
#230
b10111111110000000000000000110100 7
b10111111110000000000000000110000 "
b10111111110000000000000000110000 :
1#
#240
0#
#250
b10111111110000000000000000111000 7
b10111111110000000000000000110100 "
b10111111110000000000000000110100 :
1#
#260
0#
#270
b10111111110000000000000000111100 7
b10111111110000000000000000111000 "
b10111111110000000000000000111000 :
1#
#280
0#
#290
b10111111110000000000000001000000 7
b10111111110000000000000000111100 "
b10111111110000000000000000111100 :
1#
#300
0#
#310
b10111111110000000000000001000100 7
b10111111110000000000000001000000 "
b10111111110000000000000001000000 :
1#
#320
0#
#330
b10111111110000000000000001001000 7
b10111111110000000000000001000100 "
b10111111110000000000000001000100 :
1#
#340
0#
#350
b10111111110000000000000001001100 7
b10111111110000000000000001001000 "
b10111111110000000000000001001000 :
1#
#360
0#
#370
b10111111110000000000000001010000 7
b10111111110000000000000001001100 "
b10111111110000000000000001001100 :
1#
#380
0#
#390
b10111111110000000000000001010100 7
b10111111110000000000000001010000 "
b10111111110000000000000001010000 :
1#
#400
0#
#410
b10111111110000000000000001011000 7
b10111111110000000000000001010100 "
b10111111110000000000000001010100 :
1#
#420
0#
#430
b10111111110000000000000001011100 7
b10111111110000000000000001011000 "
b10111111110000000000000001011000 :
1#
#440
0#
#450
b10111111110000000000000001100000 7
b10111111110000000000000001011100 "
b10111111110000000000000001011100 :
1#
#460
0#
#470
b10111111110000000000000001100100 7
b10111111110000000000000001100000 "
b10111111110000000000000001100000 :
1#
#480
0#
#490
b10111111110000000000000001101000 7
b10111111110000000000000001100100 "
b10111111110000000000000001100100 :
1#
#500
0#
#510
b10111111110000000000000001101100 7
b10111111110000000000000001101000 "
b10111111110000000000000001101000 :
1#
#520
0#
#530
b10111111110000000000000001110000 7
b10111111110000000000000001101100 "
b10111111110000000000000001101100 :
1#
#540
0#
#550
b10111111110000000000000001110100 7
b10111111110000000000000001110000 "
b10111111110000000000000001110000 :
1#
#560
0#
#570
b10111111110000000000000001111000 7
b10111111110000000000000001110100 "
b10111111110000000000000001110100 :
1#
#580
0#
#590
b10111111110000000000000001111100 7
b10111111110000000000000001111000 "
b10111111110000000000000001111000 :
1#
#600
0#
#610
b10111111110000000000000010000000 7
b10111111110000000000000001111100 "
b10111111110000000000000001111100 :
1#
#620
0#
#630
b10111111110000000000000010000100 7
b10111111110000000000000010000000 "
b10111111110000000000000010000000 :
1#
#640
0#
#650
b10111111110000000000000010001000 7
b10111111110000000000000010000100 "
b10111111110000000000000010000100 :
1#
#660
0#
#670
b10111111110000000000000010001100 7
b10111111110000000000000010001000 "
b10111111110000000000000010001000 :
1#
#680
0#
#690
b10111111110000000000000010010000 7
b10111111110000000000000010001100 "
b10111111110000000000000010001100 :
1#
#700
0#
#710
b10111111110000000000000010010100 7
b10111111110000000000000010010000 "
b10111111110000000000000010010000 :
1#
#720
0#
#730
b10111111110000000000000010011000 7
b10111111110000000000000010010100 "
b10111111110000000000000010010100 :
1#
#740
0#
#750
b10111111110000000000000010011100 7
b10111111110000000000000010011000 "
b10111111110000000000000010011000 :
1#
#760
0#
#770
b10111111110000000000000010100000 7
b10111111110000000000000010011100 "
b10111111110000000000000010011100 :
1#
#780
0#
#790
b10111111110000000000000010100100 7
b10111111110000000000000010100000 "
b10111111110000000000000010100000 :
1#
#800
0#
#810
b10111111110000000000000010101000 7
b10111111110000000000000010100100 "
b10111111110000000000000010100100 :
1#
#820
0#
#830
b10111111110000000000000010101100 7
b10111111110000000000000010101000 "
b10111111110000000000000010101000 :
1#
#840
0#
#850
b10111111110000000000000010110000 7
b10111111110000000000000010101100 "
b10111111110000000000000010101100 :
1#
#860
0#
#870
b10111111110000000000000010110100 7
b10111111110000000000000010110000 "
b10111111110000000000000010110000 :
1#
#880
0#
#890
b10111111110000000000000010111000 7
b10111111110000000000000010110100 "
b10111111110000000000000010110100 :
1#
#900
0#
#910
b10111111110000000000000010111100 7
b10111111110000000000000010111000 "
b10111111110000000000000010111000 :
1#
#920
0#
#930
b10111111110000000000000011000000 7
b10111111110000000000000010111100 "
b10111111110000000000000010111100 :
1#
#940
0#
#950
b10111111110000000000000011000100 7
b10111111110000000000000011000000 "
b10111111110000000000000011000000 :
1#
#960
0#
#970
b10111111110000000000000011001000 7
b10111111110000000000000011000100 "
b10111111110000000000000011000100 :
1#
#980
0#
#990
b10111111110000000000000011001100 7
b10111111110000000000000011001000 "
b10111111110000000000000011001000 :
1#
#1000
0#
#1010
b10111111110000000000000011010000 7
b10111111110000000000000011001100 "
b10111111110000000000000011001100 :
1#
#1020
0#
#1030
b10111111110000000000000011010100 7
b10111111110000000000000011010000 "
b10111111110000000000000011010000 :
1#
#1040
0#
#1050
b10111111110000000000000011011000 7
b10111111110000000000000011010100 "
b10111111110000000000000011010100 :
1#
#1060
0#
#1070
b10111111110000000000000011011100 7
b10111111110000000000000011011000 "
b10111111110000000000000011011000 :
1#
#1080
0#
#1090
b10111111110000000000000011100000 7
b10111111110000000000000011011100 "
b10111111110000000000000011011100 :
1#
#1100
0#
#1110
b10111111110000000000000011100100 7
b10111111110000000000000011100000 "
b10111111110000000000000011100000 :
1#
#1120
0#
#1130
b10111111110000000000000011101000 7
b10111111110000000000000011100100 "
b10111111110000000000000011100100 :
1#
#1140
0#
#1150
b10111111110000000000000011101100 7
b10111111110000000000000011101000 "
b10111111110000000000000011101000 :
1#
#1160
0#
#1170
b10111111110000000000000011110000 7
b10111111110000000000000011101100 "
b10111111110000000000000011101100 :
1#
#1180
0#
#1190
b10111111110000000000000011110100 7
b10111111110000000000000011110000 "
b10111111110000000000000011110000 :
1#
#1200
0#
#1210
b10111111110000000000000011111000 7
b10111111110000000000000011110100 "
b10111111110000000000000011110100 :
1#
#1220
0#
#1230
b10111111110000000000000011111100 7
b10111111110000000000000011111000 "
b10111111110000000000000011111000 :
1#
#1240
0#
#1250
b10111111110000000000000100000000 7
b10111111110000000000000011111100 "
b10111111110000000000000011111100 :
1#
#1260
0#
#1270
b10111111110000000000000100000100 7
b10111111110000000000000100000000 "
b10111111110000000000000100000000 :
1#
#1280
0#
#1290
b10111111110000000000000100001000 7
b10111111110000000000000100000100 "
b10111111110000000000000100000100 :
1#
#1300
0#
#1310
b10111111110000000000000100001100 7
b10111111110000000000000100001000 "
b10111111110000000000000100001000 :
1#
#1320
0#
#1330
b10111111110000000000000100010000 7
b10111111110000000000000100001100 "
b10111111110000000000000100001100 :
1#
#1340
0#
#1350
b10111111110000000000000100010100 7
b10111111110000000000000100010000 "
b10111111110000000000000100010000 :
1#
#1360
0#
#1370
b10111111110000000000000100011000 7
b10111111110000000000000100010100 "
b10111111110000000000000100010100 :
1#
#1380
0#
#1390
b10111111110000000000000100011100 7
b10111111110000000000000100011000 "
b10111111110000000000000100011000 :
1#
#1400
0#
#1410
b10111111110000000000000100100000 7
b10111111110000000000000100011100 "
b10111111110000000000000100011100 :
1#
#1420
0#
#1430
b10111111110000000000000100100100 7
b10111111110000000000000100100000 "
b10111111110000000000000100100000 :
1#
#1440
0#
#1450
b10111111110000000000000100101000 7
b10111111110000000000000100100100 "
b10111111110000000000000100100100 :
1#
#1460
0#
#1470
b10111111110000000000000100101100 7
b10111111110000000000000100101000 "
b10111111110000000000000100101000 :
1#
#1480
0#
#1490
b10111111110000000000000100110000 7
b10111111110000000000000100101100 "
b10111111110000000000000100101100 :
1#
#1500
0#
#1510
b10111111110000000000000100110100 7
b10111111110000000000000100110000 "
b10111111110000000000000100110000 :
1#
#1520
0#
#1530
b10111111110000000000000100111000 7
b10111111110000000000000100110100 "
b10111111110000000000000100110100 :
1#
#1540
0#
#1550
b10111111110000000000000100111100 7
b10111111110000000000000100111000 "
b10111111110000000000000100111000 :
1#
#1560
0#
#1570
b10111111110000000000000101000000 7
b10111111110000000000000100111100 "
b10111111110000000000000100111100 :
1#
#1580
0#
#1590
b10111111110000000000000101000100 7
b10111111110000000000000101000000 "
b10111111110000000000000101000000 :
1#
#1600
0#
#1610
b10111111110000000000000101001000 7
b10111111110000000000000101000100 "
b10111111110000000000000101000100 :
1#
#1620
0#
#1630
b10111111110000000000000101001100 7
b10111111110000000000000101001000 "
b10111111110000000000000101001000 :
1#
#1640
0#
#1650
b10111111110000000000000101010000 7
b10111111110000000000000101001100 "
b10111111110000000000000101001100 :
1#
#1660
0#
#1670
b10111111110000000000000101010100 7
b10111111110000000000000101010000 "
b10111111110000000000000101010000 :
1#
#1680
0#
#1690
b10111111110000000000000101011000 7
b10111111110000000000000101010100 "
b10111111110000000000000101010100 :
1#
#1700
0#
#1710
b10111111110000000000000101011100 7
b10111111110000000000000101011000 "
b10111111110000000000000101011000 :
1#
#1720
0#
#1730
b10111111110000000000000101100000 7
b10111111110000000000000101011100 "
b10111111110000000000000101011100 :
1#
#1740
0#
#1750
b10111111110000000000000101100100 7
b10111111110000000000000101100000 "
b10111111110000000000000101100000 :
1#
#1760
0#
#1770
b10111111110000000000000101101000 7
b10111111110000000000000101100100 "
b10111111110000000000000101100100 :
1#
#1780
0#
#1790
b10111111110000000000000101101100 7
b10111111110000000000000101101000 "
b10111111110000000000000101101000 :
1#
#1800
0#
#1810
b10111111110000000000000101110000 7
b10111111110000000000000101101100 "
b10111111110000000000000101101100 :
1#
#1820
0#
#1830
b10111111110000000000000101110100 7
b10111111110000000000000101110000 "
b10111111110000000000000101110000 :
1#
#1840
0#
#1850
b10111111110000000000000101111000 7
b10111111110000000000000101110100 "
b10111111110000000000000101110100 :
1#
#1860
0#
#1870
b10111111110000000000000101111100 7
b10111111110000000000000101111000 "
b10111111110000000000000101111000 :
1#
#1880
0#
#1890
b10111111110000000000000110000000 7
b10111111110000000000000101111100 "
b10111111110000000000000101111100 :
1#
#1900
0#
#1910
b10111111110000000000000110000100 7
b10111111110000000000000110000000 "
b10111111110000000000000110000000 :
1#
#1920
0#
#1930
b10111111110000000000000110001000 7
b10111111110000000000000110000100 "
b10111111110000000000000110000100 :
1#
#1940
0#
#1950
b10111111110000000000000110001100 7
b10111111110000000000000110001000 "
b10111111110000000000000110001000 :
1#
#1960
0#
#1970
b10111111110000000000000110010000 7
b10111111110000000000000110001100 "
b10111111110000000000000110001100 :
1#
#1980
0#
#1990
b10111111110000000000000110010100 7
b10111111110000000000000110010000 "
b10111111110000000000000110010000 :
1#
#2000
0#
#2010
b10111111110000000000000110011000 7
b10111111110000000000000110010100 "
b10111111110000000000000110010100 :
1#
#2020
0#
#2030
b10111111110000000000000110011100 7
b10111111110000000000000110011000 "
b10111111110000000000000110011000 :
1#
#2040
0#
#2050
b10111111110000000000000110100000 7
b10111111110000000000000110011100 "
b10111111110000000000000110011100 :
1#
#2060
0#
#2070
b10111111110000000000000110100100 7
b10111111110000000000000110100000 "
b10111111110000000000000110100000 :
1#
#2080
0#
#2090
b10111111110000000000000110101000 7
b10111111110000000000000110100100 "
b10111111110000000000000110100100 :
1#
#2100
0#
#2110
b10111111110000000000000110101100 7
b10111111110000000000000110101000 "
b10111111110000000000000110101000 :
1#
#2120
0#
#2130
b10111111110000000000000110110000 7
b10111111110000000000000110101100 "
b10111111110000000000000110101100 :
1#
#2140
0#
#2150
b10111111110000000000000110110100 7
b10111111110000000000000110110000 "
b10111111110000000000000110110000 :
1#
#2160
0#
#2170
b10111111110000000000000110111000 7
b10111111110000000000000110110100 "
b10111111110000000000000110110100 :
1#
#2180
0#
#2190
b10111111110000000000000110111100 7
b10111111110000000000000110111000 "
b10111111110000000000000110111000 :
1#
#2200
0#
#2210
b10111111110000000000000111000000 7
b10111111110000000000000110111100 "
b10111111110000000000000110111100 :
1#
#2220
0#
#2230
b10111111110000000000000111000100 7
b10111111110000000000000111000000 "
b10111111110000000000000111000000 :
1#
#2240
0#
#2250
b10111111110000000000000111001000 7
b10111111110000000000000111000100 "
b10111111110000000000000111000100 :
1#
#2260
0#
#2270
b10111111110000000000000111001100 7
b10111111110000000000000111001000 "
b10111111110000000000000111001000 :
1#
#2280
0#
#2290
b10111111110000000000000111010000 7
b10111111110000000000000111001100 "
b10111111110000000000000111001100 :
1#
#2300
0#
#2310
b10111111110000000000000111010100 7
b10111111110000000000000111010000 "
b10111111110000000000000111010000 :
1#
#2320
0#
#2330
b10111111110000000000000111011000 7
b10111111110000000000000111010100 "
b10111111110000000000000111010100 :
1#
#2340
0#
#2350
b10111111110000000000000111011100 7
b10111111110000000000000111011000 "
b10111111110000000000000111011000 :
1#
#2360
0#
#2370
b10111111110000000000000111100000 7
b10111111110000000000000111011100 "
b10111111110000000000000111011100 :
1#
#2380
0#
#2390
b10111111110000000000000111100100 7
b10111111110000000000000111100000 "
b10111111110000000000000111100000 :
1#
#2400
0#
#2410
b10111111110000000000000111101000 7
b10111111110000000000000111100100 "
b10111111110000000000000111100100 :
1#
#2420
0#
#2430
b10111111110000000000000111101100 7
b10111111110000000000000111101000 "
b10111111110000000000000111101000 :
1#
#2440
0#
#2450
b10111111110000000000000111110000 7
b10111111110000000000000111101100 "
b10111111110000000000000111101100 :
1#
#2460
0#
#2470
b10111111110000000000000111110100 7
b10111111110000000000000111110000 "
b10111111110000000000000111110000 :
1#
#2480
0#
#2490
b10111111110000000000000111111000 7
b10111111110000000000000111110100 "
b10111111110000000000000111110100 :
1#
#2500
0#
#2510
b10111111110000000000000111111100 7
b10111111110000000000000111111000 "
b10111111110000000000000111111000 :
1#
#2520
0#
#2530
b10111111110000000000001000000000 7
b10111111110000000000000111111100 "
b10111111110000000000000111111100 :
1#
#2540
0#
#2550
b10111111110000000000001000000100 7
b10111111110000000000001000000000 "
b10111111110000000000001000000000 :
1#
#2560
0#
#2570
b10111111110000000000001000001000 7
b10111111110000000000001000000100 "
b10111111110000000000001000000100 :
1#
#2580
0#
#2590
b10111111110000000000001000001100 7
b10111111110000000000001000001000 "
b10111111110000000000001000001000 :
1#
#2600
0#
#2610
b10111111110000000000001000010000 7
b10111111110000000000001000001100 "
b10111111110000000000001000001100 :
1#
#2620
0#
#2630
b10111111110000000000001000010100 7
b10111111110000000000001000010000 "
b10111111110000000000001000010000 :
1#
#2640
0#
#2650
b10111111110000000000001000011000 7
b10111111110000000000001000010100 "
b10111111110000000000001000010100 :
1#
#2660
0#
#2670
b10111111110000000000001000011100 7
b10111111110000000000001000011000 "
b10111111110000000000001000011000 :
1#
#2680
0#
#2690
b10111111110000000000001000100000 7
b10111111110000000000001000011100 "
b10111111110000000000001000011100 :
1#
#2700
0#
#2710
b10111111110000000000001000100100 7
b10111111110000000000001000100000 "
b10111111110000000000001000100000 :
1#
#2720
0#
#2730
b10111111110000000000001000101000 7
b10111111110000000000001000100100 "
b10111111110000000000001000100100 :
1#
#2740
0#
#2750
b10111111110000000000001000101100 7
b10111111110000000000001000101000 "
b10111111110000000000001000101000 :
1#
#2760
0#
#2770
b10111111110000000000001000110000 7
b10111111110000000000001000101100 "
b10111111110000000000001000101100 :
1#
#2780
0#
#2790
b10111111110000000000001000110100 7
b10111111110000000000001000110000 "
b10111111110000000000001000110000 :
1#
#2800
0#
#2810
b10111111110000000000001000111000 7
b10111111110000000000001000110100 "
b10111111110000000000001000110100 :
1#
#2820
0#
#2830
b10111111110000000000001000111100 7
b10111111110000000000001000111000 "
b10111111110000000000001000111000 :
1#
#2840
0#
#2850
b10111111110000000000001001000000 7
b10111111110000000000001000111100 "
b10111111110000000000001000111100 :
1#
#2860
0#
#2870
b10111111110000000000001001000100 7
b10111111110000000000001001000000 "
b10111111110000000000001001000000 :
1#
#2880
0#
#2890
b10111111110000000000001001001000 7
b10111111110000000000001001000100 "
b10111111110000000000001001000100 :
1#
#2900
0#
#2910
b10111111110000000000001001001100 7
b10111111110000000000001001001000 "
b10111111110000000000001001001000 :
1#
#2920
0#
#2930
b10111111110000000000001001010000 7
b10111111110000000000001001001100 "
b10111111110000000000001001001100 :
1#
#2940
0#
#2950
b10111111110000000000001001010100 7
b10111111110000000000001001010000 "
b10111111110000000000001001010000 :
1#
#2960
0#
#2970
b10111111110000000000001001011000 7
b10111111110000000000001001010100 "
b10111111110000000000001001010100 :
1#
#2980
0#
#2990
b10111111110000000000001001011100 7
b10111111110000000000001001011000 "
b10111111110000000000001001011000 :
1#
#3000
0#
#3010
b10111111110000000000001001100000 7
b10111111110000000000001001011100 "
b10111111110000000000001001011100 :
1#
#3020
0#
#3030
b10111111110000000000001001100100 7
b10111111110000000000001001100000 "
b10111111110000000000001001100000 :
1#
#3040
0#
#3050
b10111111110000000000001001101000 7
b10111111110000000000001001100100 "
b10111111110000000000001001100100 :
1#
#3060
0#
#3070
b10111111110000000000001001101100 7
b10111111110000000000001001101000 "
b10111111110000000000001001101000 :
1#
#3080
0#
#3090
b10111111110000000000001001110000 7
b10111111110000000000001001101100 "
b10111111110000000000001001101100 :
1#
#3100
0#
#3110
b10111111110000000000001001110100 7
b10111111110000000000001001110000 "
b10111111110000000000001001110000 :
1#
#3120
0#
#3130
b10111111110000000000001001111000 7
b10111111110000000000001001110100 "
b10111111110000000000001001110100 :
1#
#3140
0#
#3150
b10111111110000000000001001111100 7
b10111111110000000000001001111000 "
b10111111110000000000001001111000 :
1#
#3160
0#
#3170
b10111111110000000000001010000000 7
b10111111110000000000001001111100 "
b10111111110000000000001001111100 :
1#
#3180
0#
#3190
b10111111110000000000001010000100 7
b10111111110000000000001010000000 "
b10111111110000000000001010000000 :
1#
#3200
0#
#3210
b10111111110000000000001010001000 7
b10111111110000000000001010000100 "
b10111111110000000000001010000100 :
1#
#3220
0#
#3230
b10111111110000000000001010001100 7
b10111111110000000000001010001000 "
b10111111110000000000001010001000 :
1#
#3240
0#
#3250
b10111111110000000000001010010000 7
b10111111110000000000001010001100 "
b10111111110000000000001010001100 :
1#
#3260
0#
#3270
b10111111110000000000001010010100 7
b10111111110000000000001010010000 "
b10111111110000000000001010010000 :
1#
#3280
0#
#3290
b10111111110000000000001010011000 7
b10111111110000000000001010010100 "
b10111111110000000000001010010100 :
1#
#3300
0#
#3310
b10111111110000000000001010011100 7
b10111111110000000000001010011000 "
b10111111110000000000001010011000 :
1#
#3320
0#
#3330
b10111111110000000000001010100000 7
b10111111110000000000001010011100 "
b10111111110000000000001010011100 :
1#
#3340
0#
#3350
b10111111110000000000001010100100 7
b10111111110000000000001010100000 "
b10111111110000000000001010100000 :
1#
#3360
0#
#3370
b10111111110000000000001010101000 7
b10111111110000000000001010100100 "
b10111111110000000000001010100100 :
1#
#3380
0#
#3390
b10111111110000000000001010101100 7
b10111111110000000000001010101000 "
b10111111110000000000001010101000 :
1#
#3400
0#
#3410
b10111111110000000000001010110000 7
b10111111110000000000001010101100 "
b10111111110000000000001010101100 :
1#
#3420
0#
#3430
b10111111110000000000001010110100 7
b10111111110000000000001010110000 "
b10111111110000000000001010110000 :
1#
#3440
0#
#3450
b10111111110000000000001010111000 7
b10111111110000000000001010110100 "
b10111111110000000000001010110100 :
1#
#3460
0#
#3470
b10111111110000000000001010111100 7
b10111111110000000000001010111000 "
b10111111110000000000001010111000 :
1#
#3480
0#
#3490
b10111111110000000000001011000000 7
b10111111110000000000001010111100 "
b10111111110000000000001010111100 :
1#
#3500
0#
#3510
b10111111110000000000001011000100 7
b10111111110000000000001011000000 "
b10111111110000000000001011000000 :
1#
#3520
0#
#3530
b10111111110000000000001011001000 7
b10111111110000000000001011000100 "
b10111111110000000000001011000100 :
1#
#3540
0#
#3550
b10111111110000000000001011001100 7
b10111111110000000000001011001000 "
b10111111110000000000001011001000 :
1#
#3560
0#
#3570
b10111111110000000000001011010000 7
b10111111110000000000001011001100 "
b10111111110000000000001011001100 :
1#
#3580
0#
#3590
b10111111110000000000001011010100 7
b10111111110000000000001011010000 "
b10111111110000000000001011010000 :
1#
#3600
0#
#3610
b10111111110000000000001011011000 7
b10111111110000000000001011010100 "
b10111111110000000000001011010100 :
1#
#3620
0#
#3630
b10111111110000000000001011011100 7
b10111111110000000000001011011000 "
b10111111110000000000001011011000 :
1#
#3640
0#
#3650
b10111111110000000000001011100000 7
b10111111110000000000001011011100 "
b10111111110000000000001011011100 :
1#
#3660
0#
#3670
b10111111110000000000001011100100 7
b10111111110000000000001011100000 "
b10111111110000000000001011100000 :
1#
#3680
0#
#3690
b10111111110000000000001011101000 7
b10111111110000000000001011100100 "
b10111111110000000000001011100100 :
1#
#3700
0#
#3710
b10111111110000000000001011101100 7
b10111111110000000000001011101000 "
b10111111110000000000001011101000 :
1#
#3720
0#
#3730
b10111111110000000000001011110000 7
b10111111110000000000001011101100 "
b10111111110000000000001011101100 :
1#
#3740
0#
#3750
b10111111110000000000001011110100 7
b10111111110000000000001011110000 "
b10111111110000000000001011110000 :
1#
#3760
0#
#3770
b10111111110000000000001011111000 7
b10111111110000000000001011110100 "
b10111111110000000000001011110100 :
1#
#3780
0#
#3790
b10111111110000000000001011111100 7
b10111111110000000000001011111000 "
b10111111110000000000001011111000 :
1#
#3800
0#
#3810
b10111111110000000000001100000000 7
b10111111110000000000001011111100 "
b10111111110000000000001011111100 :
1#
#3820
0#
#3830
b10111111110000000000001100000100 7
b10111111110000000000001100000000 "
b10111111110000000000001100000000 :
1#
#3840
0#
#3850
b10111111110000000000001100001000 7
b10111111110000000000001100000100 "
b10111111110000000000001100000100 :
1#
#3860
0#
#3870
b10111111110000000000001100001100 7
b10111111110000000000001100001000 "
b10111111110000000000001100001000 :
1#
#3880
0#
#3890
b10111111110000000000001100010000 7
b10111111110000000000001100001100 "
b10111111110000000000001100001100 :
1#
#3900
0#
#3910
b10111111110000000000001100010100 7
b10111111110000000000001100010000 "
b10111111110000000000001100010000 :
1#
#3920
0#
#3930
b10111111110000000000001100011000 7
b10111111110000000000001100010100 "
b10111111110000000000001100010100 :
1#
#3940
0#
#3950
b10111111110000000000001100011100 7
b10111111110000000000001100011000 "
b10111111110000000000001100011000 :
1#
#3960
0#
#3970
b10111111110000000000001100100000 7
b10111111110000000000001100011100 "
b10111111110000000000001100011100 :
1#
#3980
0#
#3990
b10111111110000000000001100100100 7
b10111111110000000000001100100000 "
b10111111110000000000001100100000 :
1#
#4000
0#
#4010
b10111111110000000000001100101000 7
b10111111110000000000001100100100 "
b10111111110000000000001100100100 :
1#
#4020
0#
#4030
b10111111110000000000001100101100 7
b10111111110000000000001100101000 "
b10111111110000000000001100101000 :
1#
#4040
0#
#4050
b10111111110000000000001100110000 7
b10111111110000000000001100101100 "
b10111111110000000000001100101100 :
1#
#4060
0#
#4070
b10111111110000000000001100110100 7
b10111111110000000000001100110000 "
b10111111110000000000001100110000 :
1#
#4080
0#
#4090
b10111111110000000000001100111000 7
b10111111110000000000001100110100 "
b10111111110000000000001100110100 :
1#
#4100
0#
#4110
b10111111110000000000001100111100 7
b10111111110000000000001100111000 "
b10111111110000000000001100111000 :
1#
#4120
0#
